bias_scan/clustering/__init__.py
bias_scan/clustering/_bahc.py
bias_scan/clustering/_kmeans.py
bias_scan/clustering/_kmodes.py
bias_scan-0.1.0.dist-info/LICENSE
bias_scan-0.1.0.dist-info/METADATA
bias_scan-0.1.0.dist-info/WHEEL
bias_scan-0.1.0.dist-info/RECORD
