Metadata-Version: 2.1
Name: bias-scan
Version: 0.1.0
Summary: 
License: MIT
Requires-Python: >=3.11,<4.0
Classifier: License :: OSI Approved :: MIT License
Classifier: Programming Language :: Python :: 3
Classifier: Programming Language :: Python :: 3.11
Classifier: Programming Language :: Python :: 3.12
Requires-Dist: kmodes (>=0.12.2,<0.13.0)
Requires-Dist: numpy (>=1.26.4,<2.0.0)
Requires-Dist: scikit-learn (>=1.4.1.post1,<2.0.0)
